LICENSE.txt
README.rst
setup.py
DLWrap/AssoPred.py
DLWrap/DLWrap.py
DLWrap/MLPPrediction.py
DLWrap/MLPScreenFinal.py
DLWrap/__init__.py
DLWrap.egg-info/PKG-INFO
DLWrap.egg-info/SOURCES.txt
DLWrap.egg-info/dependency_links.txt
DLWrap.egg-info/requires.txt
DLWrap.egg-info/top_level.txt